LICENSE-MIT.txt
MANIFEST.in
README.md
setup.cfg
setup.py
PyCross/TTTBoard.py
PyCross/__init__.py
PyCross/helper.py
PyCross.egg-info/PKG-INFO
PyCross.egg-info/SOURCES.txt
PyCross.egg-info/dependency_links.txt
PyCross.egg-info/top_level.txt
PyCross/gui/__init__.py
PyCross/gui/customDifficulty.glade
PyCross/gui/customDifficultyClass.py
PyCross/gui/pycrossGUI.glade
PyCross/gui/pycrossGUIClass.py
PyCross/gui/svg/__init__.py
PyCross/gui/svg/blank.svg
PyCross/gui/svg/circle.svg
PyCross/gui/svg/cross.svg
PyCross/gui/svg/iconCreator.py
bin/pycross