Metadata-Version: 1.1
Name: PyCross
Version: 0.3.1
Summary: Singleplayer/Multiplayer Tic-Tac-Toe game
Home-page: http://github.com/leosartaj/PyCross
Author: Sartaj Singh
Author-email: singhsartaj94@gmail.com
License: MIT
Keywords: game tic-tac-toe tictactoe play
Platform: UNKNOWN
Classifier: Development Status :: 3 - Alpha
Classifier: License :: OSI Approved :: MIT License
Classifier: Environment :: X11 Applications :: GTK
Classifier: Environment :: Console
Classifier: Natural Language :: English
Classifier: Programming Language :: Python :: 2.7
Classifier: Topic :: Games/Entertainment :: Board Games
